{
  "kind": "collectionType",
  "collectionName": "sites",
  "info": {
    "singularName": "site",
    "pluralName": "sites",
    "displayName": "Site",
    "description": ""
  },
  "options": {
    "draftAndPublish": true
  },
  "attributes": {
    "name": {
      "type": "string"
    },
    "url": {
      "type": "string"
    },
    "slug": {
      "type": "string"
    },
    "id_site": {
      "type": "integer"
    },
    "side_navbars": {
      "type": "relation",
      "relation": "oneToMany",
      "target": "api::side-navbar.side-navbar",
      "mappedBy": "site"
    },
    "service_flow": {
      "type": "relation",
      "relation": "manyToOne",
      "target": "api::service-flow.service-flow",
      "mappedBy": "site"
    },
    "theme": {
      "type": "relation",
      "relation": "oneToMany",
      "target": "api::theme.theme",
      "inversedBy": "sites"
    }
  }
}
